untestable/__init__.py
untestable/arg_driven_app.py
untestable/bitbucket_app.py
untestable/commands/__init__.py
untestable/commands/command.py
untestable/commands/g_user_command.py
untestable/commands/g_user_repos_command.py
untestable/di/__init__.py
untestable/di/console_config.py
untestable/flow/__init__.py
untestable/flow/flows.py
untestable/flow/simple_credentials_collection_flow.py
untestable/i_o/__init__.py
untestable/i_o/bitbucket_client.py
untestable/i_o/console_io.py
untestable/i_o/credential_persistence.py
untestable/i_o/credentials.py
untestable/i_o/file_based_credential_persistence.py
untestable/i_o/rest_bitbucket_client.py
untestable/i_o/rest_bitbucket_client_config.json
untestable/i_o/user_io.py
untestable-1.0.0.dist-info/DESCRIPTION.rst
untestable-1.0.0.dist-info/METADATA
untestable-1.0.0.dist-info/RECORD
untestable-1.0.0.dist-info/WHEEL
untestable-1.0.0.dist-info/entry_points.txt
untestable-1.0.0.dist-info/metadata.json
untestable-1.0.0.dist-info/top_level.txt
