Metadata-Version: 2.0
Name: untestable
Version: 1.0.0
Summary: A python version of the untestable application at https://bitbucket.org/tcbakes/untestable
Home-page: https://bitbucket.org/tcbakes/untestable_py
Author: Tristan Baker
Author-email: tcbakes@gmail.com
License: MIT
Keywords: sample unittest design
Platform: UNKNOWN
Classifier: Development Status :: 3 - Alpha
Classifier: Intended Audience :: Developers
Classifier: Topic :: Software Development
Classifier: License :: OSI Approved :: MIT License
Classifier: Programming Language :: Python :: 2.7
Requires-Dist: requests (==2.8.1)
Provides-Extra: test
Requires-Dist: coverage; extra == 'test'
